[
  {
    "title": "Project Euler",
    "website": "www.hackerrank.com/contests/projecteuler/challenges/",
    "start": "09/04/2021",
    "end": "09/05/2021",
    "organisation": "Hackerrank",
    "location": "Online"
  },
  {
    "title": "236th LeetCode Weekly Contest",
    "website": "www.leetcode.com/contest/weekly-contest-236",
    "start": "11/10/2020",
    "end": "11/10/2021",
    "organisation": "Leetcode",
    "location": "Online"
  },
  {
    "title": "Celebrate Neurodiversity Coding Contest 2021",
    "website": "www.hackerrank.com/competitions/celebrate-diversity-month-2021",
    "start": "06/02/2021",
    "end": "07/06/2021",
    "organisation": "Hackerrank",
    "location": "Online"
  },
  {
    "title": "Codeheat",
    "website": "www.codeheat.org",
    "start": "01/10/2020",
    "end": "01/06/2021",
    "organisation": "FOSSASIA",
    "location": "Online"
  },
  {
    "title": "Career Bootcamp",
    "website": "codingblocks.com/",
    "start": "20/11/2020",
    "end": "22/11/2021",
    "organisation": "Coding Blocks",
    "location": "Online"
  },
  {
    "title": "Travel transform New Gen Coding",
    "website": "www.interviewbit.com/contest/travel-transforms-2021--discover-what-you-do-best/",
    "start": "16/10/2020",
    "end": "18/10/2021",
    "organisation": "InterviewBit",
    "location": "Online"
  },
    {
    "title": "GIRLSCRIPT SUMMER OF CODE",
    "website": "gssoc.girlscript.tech/",
    "start": "10/03/2021",
    "end": "31/05/2021",
    "organisation": "GirlScript Foundation",
    "location": "Online"
  },
  {
    "title":"Google Summer of Code",
    "website":"summerofcode.withgoogle.com/",
    "start":"17/05/2021",
    "end":"23/08/2021",
    "organisation":"Multiple organisations like FOSSASIA,Redhat,ASF and many more ",  
    "location":"Online"
  }
]

